Metadata-Version: 1.0
Name: picom
Version: 0.5.4
Summary: Help communicating Iot with Raspberry Pi
Home-page: https://github.com/Thumberd/PiCom
Author: Jérémy Albrecht
Author-email: ajeremyalbrecht@gmail.com
License: MIT
Platform: UNKNOWN
